[
  {
    "ContainingType": "ProjectManager.Controllers.AuthController",
    "Method": "Login",
    "RelativePath": "Auth/login",
    "HttpMethod": "POST",
    "IsController": true,
    "Order": 0,
    "Parameters": [
      {
        "Name": "request",
        "Type": "Microsoft.AspNetCore.Identity.Data.LoginRequest",
        "IsRequired": true
      }
    ],
    "ReturnTypes": []
  },
  {
    "ContainingType": "ProjectManager.Controllers.ProjectsController",
    "Method": "CreateProject",
    "RelativePath": "Projects/CreateProject",
    "HttpMethod": "POST",
    "IsController": true,
    "Order": 0,
    "Parameters": [
      {
        "Name": "projectData",
        "Type": "Models.Project.Models.ProjectData",
        "IsRequired": true
      }
    ],
    "ReturnTypes": [
      {
        "Type": "Models.ProjectResponse",
        "MediaTypes": [
          "text/plain",
          "application/json",
          "text/json"
        ],
        "StatusCode": 200
      }
    ]
  },
  {
    "ContainingType": "ProjectManager.Controllers.ProjectsController",
    "Method": "DeleteProject",
    "RelativePath": "Projects/DeleteProject",
    "HttpMethod": "GET",
    "IsController": true,
    "Order": 0,
    "Parameters": [
      {
        "Name": "projectId",
        "Type": "System.Int32",
        "IsRequired": false
      }
    ],
    "ReturnTypes": [
      {
        "Type": "Models.ProjectResponse",
        "MediaTypes": [
          "text/plain",
          "application/json",
          "text/json"
        ],
        "StatusCode": 200
      }
    ]
  },
  {
    "ContainingType": "ProjectManager.Controllers.ProjectsController",
    "Method": "GetAllProjects",
    "RelativePath": "Projects/GetAllProjects/{page}/{size}",
    "HttpMethod": "GET",
    "IsController": true,
    "Order": 0,
    "Parameters": [
      {
        "Name": "page",
        "Type": "System.Int32",
        "IsRequired": true
      },
      {
        "Name": "size",
        "Type": "System.Int32",
        "IsRequired": true
      }
    ],
    "ReturnTypes": [
      {
        "Type": "Models.ProjectListResponse",
        "MediaTypes": [
          "text/plain",
          "application/json",
          "text/json"
        ],
        "StatusCode": 200
      }
    ]
  },
  {
    "ContainingType": "ProjectManager.Controllers.ProjectsController",
    "Method": "GetProjectAsync",
    "RelativePath": "Projects/GetProject",
    "HttpMethod": "GET",
    "IsController": true,
    "Order": 0,
    "Parameters": [
      {
        "Name": "projectId",
        "Type": "System.Int32",
        "IsRequired": false
      }
    ],
    "ReturnTypes": [
      {
        "Type": "Models.ProjectResponse",
        "MediaTypes": [
          "text/plain",
          "application/json",
          "text/json"
        ],
        "StatusCode": 200
      }
    ]
  },
  {
    "ContainingType": "ProjectManager.Controllers.ProjectsController",
    "Method": "UpdateProject",
    "RelativePath": "Projects/UpdateProject",
    "HttpMethod": "POST",
    "IsController": true,
    "Order": 0,
    "Parameters": [
      {
        "Name": "projectData",
        "Type": "Models.Project.Models.ProjectData",
        "IsRequired": true
      }
    ],
    "ReturnTypes": [
      {
        "Type": "Models.ProjectResponse",
        "MediaTypes": [
          "text/plain",
          "application/json",
          "text/json"
        ],
        "StatusCode": 200
      }
    ]
  },
  {
    "ContainingType": "ProjectManager.Controllers.ProjectsController",
    "Method": "UpdateTaskProject",
    "RelativePath": "Projects/UpdateTaskProject",
    "HttpMethod": "POST",
    "IsController": true,
    "Order": 0,
    "Parameters": [
      {
        "Name": "projectTask",
        "Type": "Models.Project.Models.ProjectTask",
        "IsRequired": true
      }
    ],
    "ReturnTypes": [
      {
        "Type": "Models.TaskResponse",
        "MediaTypes": [
          "text/plain",
          "application/json",
          "text/json"
        ],
        "StatusCode": 200
      }
    ]
  }
]